config/advanced_config.yaml
config/basic_config.yaml
config/default_config.yaml
config/high_performance_config.yaml
config/historical_logs_config.yaml
config/microservices_config.yaml
config/multi_file_config.yaml
config/ultra_performance_config.yaml
demo_patterns/api_request_detailed.json
demo_patterns/custom_web_access.json
error_patterns/api_gateway_timeout.json
error_patterns/circuit_breaker_open.json
error_patterns/kubernetes_pod_evicted.json
error_scenarios/microservice_cascade_failure.json
log_generator/__init__.py
log_generator/cli.py
log_generator/core/__init__.py
log_generator/core/config.py
log_generator/core/engine.py
log_generator/core/exceptions.py
log_generator/core/factory.py
log_generator/core/interfaces.py
log_generator/core/log_analyzer.py
log_generator/core/log_validator.py
log_generator/core/models.py
log_generator/core/output_factory.py
log_generator/core/performance.py
log_generator/generators/__init__.py
log_generator/generators/apache.py
log_generator/generators/django.py
log_generator/generators/docker.py
log_generator/generators/fastapi.py
log_generator/generators/kubernetes.py
log_generator/generators/mysql.py
log_generator/generators/nginx.py
log_generator/generators/postgresql.py
log_generator/generators/syslog.py
log_generator/outputs/__init__.py
log_generator/outputs/console_handler.py
log_generator/outputs/file_handler.py
log_generator/outputs/json_handler.py
log_generator/outputs/multi_file_handler.py
log_generator/outputs/network_handler.py
log_generator/patterns/__init__.py
log_generator/patterns/error_manager.py
log_generator/patterns/error_patterns.py
log_generator/patterns/faker_integration.py
log_generator/patterns/frequency_controller.py
log_generator/patterns/pattern_manager.py
log_generator/patterns/template_parser.py
log_generator/patterns/validator.py
log_generator_tool-1.0.1.dist-info/licenses/LICENSE
scripts/deploy.py
log_generator_tool-1.0.1.dist-info/METADATA
log_generator_tool-1.0.1.dist-info/WHEEL
log_generator_tool-1.0.1.dist-info/entry_points.txt
log_generator_tool-1.0.1.dist-info/top_level.txt
log_generator_tool-1.0.1.dist-info/RECORD
