Metadata-Version: 2.4
Name: log-generator-tool
Version: 1.0.1
Summary: Automatic log generation tool for log analyzer development and testing
Home-page: https://github.com/log-generator/log-generator-tool
Author: Log Generator Team
Author-email: Log Generator Team <team@loggenerator.dev>
Maintainer-email: Log Generator Team <team@loggenerator.dev>
License: MIT
Project-URL: Homepage, https://github.com/log-generator/log-generator-tool
Project-URL: Documentation, https://log-generator-tool.readthedocs.io/
Project-URL: Repository, https://github.com/log-generator/log-generator-tool.git
Project-URL: Bug Reports, https://github.com/log-generator/log-generator-tool/issues
Project-URL: Changelog, https://github.com/log-generator/log-generator-tool/blob/main/CHANGELOG.md
Keywords: log,generator,testing,development,analysis,nginx,apache,syslog,fastapi,django,docker,kubernetes
Classifier: Development Status :: 4 - Beta
Classifier: Intended Audience :: Developers
Classifier: Intended Audience :: System Administrators
Classifier: License :: OSI Approved :: MIT License
Classifier: Operating System :: OS Independent
Classifier: Programming Language :: Python :: 3
Classifier: Programming Language :: Python :: 3.8
Classifier: Programming Language :: Python :: 3.9
Classifier: Programming Language :: Python :: 3.10
Classifier: Programming Language :: Python :: 3.11
Classifier: Programming Language :: Python :: 3.12
Classifier: Topic :: Software Development :: Testing
Classifier: Topic :: System :: Logging
Classifier: Topic :: System :: Monitoring
Classifier: Topic :: Utilities
Classifier: Environment :: Console
Classifier: Natural Language :: English
Classifier: Natural Language :: Korean
Requires-Python: >=3.8
License-File: LICENSE
Requires-Dist: typer>=0.9.0
Requires-Dist: pyyaml>=6.0
Requires-Dist: faker>=19.0.0
Requires-Dist: rich>=13.0.0
Requires-Dist: click>=8.0.0
Provides-Extra: dev
Requires-Dist: pytest>=7.4.0; extra == "dev"
Requires-Dist: pytest-cov>=4.1.0; extra == "dev"
Requires-Dist: pytest-mock>=3.11.1; extra == "dev"
Requires-Dist: pytest-asyncio>=0.21.0; extra == "dev"
Requires-Dist: black>=23.7.0; extra == "dev"
Requires-Dist: flake8>=6.0.0; extra == "dev"
Requires-Dist: mypy>=1.5.0; extra == "dev"
Requires-Dist: isort>=5.12.0; extra == "dev"
Requires-Dist: pre-commit>=3.3.0; extra == "dev"
Requires-Dist: bandit>=1.7.5; extra == "dev"
Requires-Dist: safety>=2.3.0; extra == "dev"
Provides-Extra: network
Requires-Dist: requests>=2.31.0; extra == "network"
Requires-Dist: aiohttp>=3.8.0; extra == "network"
Provides-Extra: monitoring
Requires-Dist: psutil>=5.9.0; extra == "monitoring"
Requires-Dist: prometheus-client>=0.17.0; extra == "monitoring"
Provides-Extra: performance
Requires-Dist: uvloop>=0.17.0; sys_platform != "win32" and extra == "performance"
Requires-Dist: orjson>=3.9.0; extra == "performance"
Provides-Extra: all
Requires-Dist: requests>=2.31.0; extra == "all"
Requires-Dist: aiohttp>=3.8.0; extra == "all"
Requires-Dist: psutil>=5.9.0; extra == "all"
Requires-Dist: prometheus-client>=0.17.0; extra == "all"
Requires-Dist: uvloop>=0.17.0; sys_platform != "win32" and extra == "all"
Requires-Dist: orjson>=3.9.0; extra == "all"
Dynamic: author
Dynamic: home-page
Dynamic: license-file
Dynamic: requires-python
